{
  "consecutive_no_quality_updates": 3,
  "last_run_utc": "2026-03-07T12:41:00Z",
  "last_result": "no_reply",
  "last_pushed": [
    {
      "handle": "@elonmusk",
      "tweet_id": "2030152895149265404",
      "link": "https://x.com/elonmusk/status/2030152895149265404",
      "pushed_at_utc": "2026-03-07T07:40:00Z"
    }
  ],
  "notes": "6551 primary still unavailable (TWITTER_TOKEN missing). Fallback checks via r.jina/x profile pages for 8 accounts showed no newly verifiable high-quality incremental updates in last 24h; visible high-signal IDs were already pushed."
}