{
  "updatedAt": "2026-03-29T07:25:59.617Z",
  "items": {
    "1336382": {
      "id": "1336382",
      "market": "Another critical Cloudflare incident by March 31, 2026?",
      "category": "政治",
      "direction": "No",
      "prob": 0.9565,
      "spread": 0.005,
      "liquidity": 94727.70577399989,
      "endDate": "2026-03-31T00:00:00Z"
    },
    "1467763": {
      "id": "1467763",
      "market": "Will Crude Oil (CL) hit (HIGH) $120 by end of March?",
      "category": "加密",
      "direction": "No",
      "prob": 0.9475,
      "spread": 0.003,
      "liquidity": 6518743.663439971,
      "endDate": "2026-03-31T00:00:00Z"
    },
    "1692192": {
      "id": "1692192",
      "market": "Will the price of Bitcoin be above $64,000 on March 30?",
      "category": "加密",
      "direction": "Yes",
      "prob": 0.887,
      "spread": 0.008,
      "liquidity": 67163.12991999989,
      "endDate": "2026-03-30T16:00:00Z"
    },
    "1692204": {
      "id": "1692204",
      "market": "Will the price of Bitcoin be above $70,000 on March 30?",
      "category": "加密",
      "direction": "No",
      "prob": 0.947,
      "spread": 0.004,
      "liquidity": 70492.57512100003,
      "endDate": "2026-03-30T16:00:00Z"
    }
  }
}